{"name":"Projecthex","tagline":"Project-based hex editor","body":"# ProjectHex #\r\n\r\nAuthor: [Michael Gaisser](mailto:mjgaisser@gmail.com)\r\nVersion: 0.0.4\r\nDate: 130910\r\n\r\nA project-based hex editor, with full tree navigation of binary files based on\r\nproject files created by the user. The projects define the file structure and\r\n\"building blocks\" of the file, so defining a node once allows the use of the\r\nnode throughout the entire binary.\r\n\r\n_______________________\r\n### Version History ###\r\n\r\n0.0.4, 130910\r\n* [ADD] Started laying out additional project-level defaults for StringVar and BoolVar\r\n* [ADD] Operators for most VarTypes\r\n* [UPD] Reading a Binary now implements a DeepCopy() method when loading Types\r\n* [UPD] License changed to MPL 2.0\r\n\r\n0.0.3, 130701\r\n* [ADD] Additional commenting\r\n* [ADD] Serializable\r\n* [UPD] Modified some internal properties\r\n\r\n0.0.2, 130613\r\n* Text updates\r\n\r\n0.0.1, 130421\r\n* Initial Upload\r\n\r\n### Installation Notes ###\r\nRequires the use of [MikeG621/Common](https://github.com/MikeG621/Common).\r\n\r\n_______________________________\r\n#### Copyright Information ####\r\nCopyright © Michael Gaisser, 2012-\r\n\r\nThis software is subject to the terms of the Mozilla Public\r\nLicense, v. 2.0. If a copy of the MPL (License.txt) was not distributed\r\nwith this file, You can obtain one at http://mozilla.org/MPL/2.0/","google":"","note":"Don't delete this file! It's used internally to help with page regeneration."}